[{"l":"https://storage.googleapis.com/ltesoup/lte/9046_8663.jpeg","s":"https://storage.googleapis.com/ltesoup/lte/9046_8663.jpeg"},{"l":"https://storage.googleapis.com/ltesoup/lte/2688_9b37.jpeg","s":"https://storage.googleapis.com/ltesoup/lte/2688_9b37.jpeg"},{"l":"https://storage.googleapis.com/ltesoup/lte/6628_7446.png","s":"https://storage.googleapis.com/ltesoup/lte/6628_7446.png"},{"l":"https://storage.googleapis.com/ltesoup/lte/4241_6a44.jpeg","s":"https://storage.googleapis.com/ltesoup/lte/4241_6a44.jpeg"},{"l":"https://storage.googleapis.com/ltesoup/lte/4175_c2d1.jpeg","s":"https://storage.googleapis.com/ltesoup/lte/4175_c2d1.jpeg"},{"l":"https://storage.googleapis.com/ltesoup/lte/0388_af33.gif","s":"https://storage.googleapis.com/ltesoup/lte/0388_af33.gif"},{"l":"https://storage.googleapis.com/ltesoup/lte/5376_d2e4.jpeg","s":"https://storage.googleapis.com/ltesoup/lte/5376_d2e4.jpeg"},{"l":"https://storage.googleapis.com/ltesoup/lte/3988_09b2.gif","s":"https://storage.googleapis.com/ltesoup/lte/3988_09b2.gif"},{"l":"https://storage.googleapis.com/ltesoup/lte/2702_81b1.jpeg","s":"https://storage.googleapis.com/ltesoup/lte/2702_81b1.jpeg"},{"l":"https://storage.googleapis.com/ltesoup/lte/6859_7134.jpeg","s":"https://storage.googleapis.com/ltesoup/lte/6859_7134.jpeg"},{"l":"https://storage.googleapis.com/ltesoup/lte/9745_3543.jpeg","s":"https://storage.googleapis.com/ltesoup/lte/9745_3543.jpeg"},{"l":"https://storage.googleapis.com/ltesoup/lte/1275_1659.gif","s":"https://storage.googleapis.com/ltesoup/lte/1275_1659.gif"},{"l":"https://storage.googleapis.com/ltesoup/lte/3281_440c.gif","s":"https://storage.googleapis.com/ltesoup/lte/3281_440c.gif"},{"l":"https://storage.googleapis.com/ltesoup/lte/6920_8c6e.gif","s":"https://storage.googleapis.com/ltesoup/lte/6920_8c6e.gif"},{"l":"https://storage.googleapis.com/ltesoup/lte/1215_e531.jpeg","s":"https://storage.googleapis.com/ltesoup/lte/1215_e531.jpeg"},{"l":"https://storage.googleapis.com/ltesoup/lte/8856_aab6.jpeg","s":"https://storage.googleapis.com/ltesoup/lte/8856_aab6.jpeg"},{"l":"https://storage.googleapis.com/ltesoup/lte/0304_b23d.jpeg","s":"https://storage.googleapis.com/ltesoup/lte/0304_b23d.jpeg"},{"l":"https://storage.googleapis.com/ltesoup/lte/4741_3e22.png","s":"https://storage.googleapis.com/ltesoup/lte/4741_3e22.png"},{"l":"https://storage.googleapis.com/ltesoup/lte/1109_5b64.jpeg","s":"https://storage.googleapis.com/ltesoup/lte/1109_5b64.jpeg"},{"l":"https://storage.googleapis.com/ltesoup/lte/7754_1994.jpeg","s":"https://storage.googleapis.com/ltesoup/lte/7754_1994.jpeg"}]