[{"l":"https://storage.googleapis.com/ltesoup/lte/7994_23f8.jpeg","s":"https://storage.googleapis.com/ltesoup/lte/7994_23f8.jpeg"},{"l":"https://storage.googleapis.com/ltesoup/lte/8672_372a.jpeg","s":"https://storage.googleapis.com/ltesoup/lte/8672_372a.jpeg"},{"l":"https://storage.googleapis.com/ltesoup/lte/7114_9e81.jpeg","s":"https://storage.googleapis.com/ltesoup/lte/7114_9e81.jpeg"},{"l":"https://storage.googleapis.com/ltesoup/lte/7584_2f0b.jpeg","s":"https://storage.googleapis.com/ltesoup/lte/7584_2f0b.jpeg"},{"l":"https://storage.googleapis.com/ltesoup/lte/9964_7688.jpeg","s":"https://storage.googleapis.com/ltesoup/lte/9964_7688.jpeg"},{"l":"https://storage.googleapis.com/ltesoup/lte/7640_817d.jpeg","s":"https://storage.googleapis.com/ltesoup/lte/7640_817d.jpeg"},{"l":"https://storage.googleapis.com/ltesoup/lte/5712_e451.jpeg","s":"https://storage.googleapis.com/ltesoup/lte/5712_e451.jpeg"},{"l":"https://storage.googleapis.com/ltesoup/lte/2299_b2a8.jpeg","s":"https://storage.googleapis.com/ltesoup/lte/2299_b2a8.jpeg"},{"l":"https://storage.googleapis.com/ltesoup/lte/5727_e3ba.jpeg","s":"https://storage.googleapis.com/ltesoup/lte/5727_e3ba.jpeg"},{"l":"https://storage.googleapis.com/ltesoup/lte/0880_22c0.gif","s":"https://storage.googleapis.com/ltesoup/lte/0880_22c0.gif"},{"l":"https://storage.googleapis.com/ltesoup/lte/8830_d724.jpeg","s":"https://storage.googleapis.com/ltesoup/lte/8830_d724.jpeg"},{"l":"https://storage.googleapis.com/ltesoup/lte/6516_a766.jpeg","s":"https://storage.googleapis.com/ltesoup/lte/6516_a766.jpeg"},{"l":"https://storage.googleapis.com/ltesoup/lte/5405_7ba0.jpeg","s":"https://storage.googleapis.com/ltesoup/lte/5405_7ba0.jpeg"},{"l":"https://storage.googleapis.com/ltesoup/lte/9395_5f69.gif","s":"https://storage.googleapis.com/ltesoup/lte/9395_5f69.gif"},{"l":"https://storage.googleapis.com/ltesoup/lte/0003_6d39.jpeg","s":"https://storage.googleapis.com/ltesoup/lte/0003_6d39.jpeg"},{"l":"https://storage.googleapis.com/ltesoup/lte/7762_71b4.jpeg","s":"https://storage.googleapis.com/ltesoup/lte/7762_71b4.jpeg"},{"l":"https://storage.googleapis.com/ltesoup/lte/2824_8a15.jpeg","s":"https://storage.googleapis.com/ltesoup/lte/2824_8a15.jpeg"},{"l":"https://storage.googleapis.com/ltesoup/lte/7571_75a0.jpeg","s":"https://storage.googleapis.com/ltesoup/lte/7571_75a0.jpeg"},{"l":"https://storage.googleapis.com/ltesoup/lte/0357_523a.jpeg","s":"https://storage.googleapis.com/ltesoup/lte/0357_523a.jpeg"},{"l":"https://storage.googleapis.com/ltesoup/lte/0364_d771.gif","s":"https://storage.googleapis.com/ltesoup/lte/0364_d771.gif"}]