[{"l":"https://storage.googleapis.com/ltesoup/lte/5418_6e29.png","s":"https://storage.googleapis.com/ltesoup/lte/5418_6e29.png"},{"l":"https://storage.googleapis.com/ltesoup/lte/5426_459d.jpeg","s":"https://storage.googleapis.com/ltesoup/lte/5426_459d.jpeg"},{"l":"https://storage.googleapis.com/ltesoup/lte/5412_d342.gif","s":"https://storage.googleapis.com/ltesoup/lte/5412_d342.gif"},{"l":"https://storage.googleapis.com/ltesoup/lte/5732_3c44.gif","s":"https://storage.googleapis.com/ltesoup/lte/5732_3c44.gif"},{"l":"https://storage.googleapis.com/ltesoup/lte/9171_f3e2.gif","s":"https://storage.googleapis.com/ltesoup/lte/9171_f3e2.gif"},{"l":"https://storage.googleapis.com/ltesoup/lte/9865_ad60.gif","s":"https://storage.googleapis.com/ltesoup/lte/9865_ad60.gif"},{"l":"https://storage.googleapis.com/ltesoup/lte/8812_bd52.jpeg","s":"https://storage.googleapis.com/ltesoup/lte/8812_bd52.jpeg"},{"l":"https://storage.googleapis.com/ltesoup/lte/8098_36bf.jpeg","s":"https://storage.googleapis.com/ltesoup/lte/8098_36bf.jpeg"},{"l":"https://storage.googleapis.com/ltesoup/lte/1159_5b11.gif","s":"https://storage.googleapis.com/ltesoup/lte/1159_5b11.gif"},{"l":"https://storage.googleapis.com/ltesoup/lte/7071_453d.jpeg","s":"https://storage.googleapis.com/ltesoup/lte/7071_453d.jpeg"},{"l":"https://storage.googleapis.com/ltesoup/lte/7285_1702.gif","s":"https://storage.googleapis.com/ltesoup/lte/7285_1702.gif"},{"l":"https://storage.googleapis.com/ltesoup/lte/5353_4e3f.gif","s":"https://storage.googleapis.com/ltesoup/lte/5353_4e3f.gif"},{"l":"https://storage.googleapis.com/ltesoup/lte/4380_4dce.jpeg","s":"https://storage.googleapis.com/ltesoup/lte/4380_4dce.jpeg"},{"l":"https://storage.googleapis.com/ltesoup/lte/9767_3790.gif","s":"https://storage.googleapis.com/ltesoup/lte/9767_3790.gif"},{"l":"https://storage.googleapis.com/ltesoup/lte/8230_9d12.gif","s":"https://storage.googleapis.com/ltesoup/lte/8230_9d12.gif"},{"l":"https://storage.googleapis.com/ltesoup/lte/2853_e556.jpeg","s":"https://storage.googleapis.com/ltesoup/lte/2853_e556.jpeg"},{"l":"https://storage.googleapis.com/ltesoup/lte/2075_78db.jpeg","s":"https://storage.googleapis.com/ltesoup/lte/2075_78db.jpeg"},{"l":"https://storage.googleapis.com/ltesoup/lte/2322_2c23.jpeg","s":"https://storage.googleapis.com/ltesoup/lte/2322_2c23.jpeg"},{"l":"https://storage.googleapis.com/ltesoup/lte/9206_3943.jpeg","s":"https://storage.googleapis.com/ltesoup/lte/9206_3943.jpeg"},{"l":"https://storage.googleapis.com/ltesoup/lte/2317_0c60.jpeg","s":"https://storage.googleapis.com/ltesoup/lte/2317_0c60.jpeg"}]