[{"l":"https://storage.googleapis.com/ltesoup/lte/9808_0c1a.jpeg","s":"https://storage.googleapis.com/ltesoup/lte/9808_0c1a.jpeg"},{"l":"https://storage.googleapis.com/ltesoup/lte/9442_bb22.jpeg","s":"https://storage.googleapis.com/ltesoup/lte/9442_bb22.jpeg"},{"l":"https://storage.googleapis.com/ltesoup/lte/8262_23cf.jpeg","s":"https://storage.googleapis.com/ltesoup/lte/8262_23cf.jpeg"},{"l":"https://storage.googleapis.com/ltesoup/lte/1992_9dfe.gif","s":"https://storage.googleapis.com/ltesoup/lte/1992_9dfe.gif"},{"l":"https://storage.googleapis.com/ltesoup/lte/2875_078d.gif","s":"https://storage.googleapis.com/ltesoup/lte/2875_078d.gif"},{"l":"https://storage.googleapis.com/ltesoup/lte/4114_8a15.jpeg","s":"https://storage.googleapis.com/ltesoup/lte/4114_8a15.jpeg"},{"l":"https://storage.googleapis.com/ltesoup/lte/1191_812b.png","s":"https://storage.googleapis.com/ltesoup/lte/1191_812b.png"},{"l":"https://storage.googleapis.com/ltesoup/lte/0645_9ff7.gif","s":"https://storage.googleapis.com/ltesoup/lte/0645_9ff7.gif"},{"l":"https://storage.googleapis.com/ltesoup/lte/0046_1802.jpeg","s":"https://storage.googleapis.com/ltesoup/lte/0046_1802.jpeg"},{"l":"https://storage.googleapis.com/ltesoup/lte/9718_93cd.jpeg","s":"https://storage.googleapis.com/ltesoup/lte/9718_93cd.jpeg"},{"l":"https://storage.googleapis.com/ltesoup/lte/3015_4c3b.jpeg","s":"https://storage.googleapis.com/ltesoup/lte/3015_4c3b.jpeg"},{"l":"https://storage.googleapis.com/ltesoup/lte/0538_13be.jpeg","s":"https://storage.googleapis.com/ltesoup/lte/0538_13be.jpeg"},{"l":"https://storage.googleapis.com/ltesoup/lte/7822_72de.gif","s":"https://storage.googleapis.com/ltesoup/lte/7822_72de.gif"},{"l":"https://storage.googleapis.com/ltesoup/lte/3285_1a50.gif","s":"https://storage.googleapis.com/ltesoup/lte/3285_1a50.gif"},{"l":"https://storage.googleapis.com/ltesoup/lte/1290_e55b.gif","s":"https://storage.googleapis.com/ltesoup/lte/1290_e55b.gif"},{"l":"https://storage.googleapis.com/ltesoup/lte/9457_010d.png","s":"https://storage.googleapis.com/ltesoup/lte/9457_010d.png"},{"l":"https://storage.googleapis.com/ltesoup/lte/7183_a20a.jpeg","s":"https://storage.googleapis.com/ltesoup/lte/7183_a20a.jpeg"},{"l":"https://storage.googleapis.com/ltesoup/lte/0452_c315.jpeg","s":"https://storage.googleapis.com/ltesoup/lte/0452_c315.jpeg"},{"l":"https://storage.googleapis.com/ltesoup/lte/9788_086b.jpeg","s":"https://storage.googleapis.com/ltesoup/lte/9788_086b.jpeg"},{"l":"https://storage.googleapis.com/ltesoup/lte/4490_28b4.gif","s":"https://storage.googleapis.com/ltesoup/lte/4490_28b4.gif"}]