[{"l":"https://storage.googleapis.com/ltesoup/lte/1010_c6e9.jpeg","s":"https://storage.googleapis.com/ltesoup/lte/1010_c6e9.jpeg"},{"l":"https://storage.googleapis.com/ltesoup/lte/8630_0850.jpeg","s":"https://storage.googleapis.com/ltesoup/lte/8630_0850.jpeg"},{"l":"https://storage.googleapis.com/ltesoup/lte/7216_b4e0.gif","s":"https://storage.googleapis.com/ltesoup/lte/7216_b4e0.gif"},{"l":"https://storage.googleapis.com/ltesoup/lte/0285_9d81.jpeg","s":"https://storage.googleapis.com/ltesoup/lte/0285_9d81.jpeg"},{"l":"https://storage.googleapis.com/ltesoup/lte/6025_fd12.jpeg","s":"https://storage.googleapis.com/ltesoup/lte/6025_fd12.jpeg"},{"l":"https://storage.googleapis.com/ltesoup/lte/8097_cbed.jpeg","s":"https://storage.googleapis.com/ltesoup/lte/8097_cbed.jpeg"},{"l":"https://storage.googleapis.com/ltesoup/lte/7496_f431.jpeg","s":"https://storage.googleapis.com/ltesoup/lte/7496_f431.jpeg"},{"l":"https://storage.googleapis.com/ltesoup/lte/7290_2d35.jpeg","s":"https://storage.googleapis.com/ltesoup/lte/7290_2d35.jpeg"},{"l":"https://storage.googleapis.com/ltesoup/lte/6392_f1f1.jpeg","s":"https://storage.googleapis.com/ltesoup/lte/6392_f1f1.jpeg"},{"l":"https://storage.googleapis.com/ltesoup/lte/1867_8662.png","s":"https://storage.googleapis.com/ltesoup/lte/1867_8662.png"},{"l":"https://storage.googleapis.com/ltesoup/lte/5731_af1e.jpeg","s":"https://storage.googleapis.com/ltesoup/lte/5731_af1e.jpeg"},{"l":"https://storage.googleapis.com/ltesoup/lte/2925_0b6c.jpeg","s":"https://storage.googleapis.com/ltesoup/lte/2925_0b6c.jpeg"},{"l":"https://storage.googleapis.com/ltesoup/lte/8768_24a7.jpeg","s":"https://storage.googleapis.com/ltesoup/lte/8768_24a7.jpeg"},{"l":"https://storage.googleapis.com/ltesoup/lte/9975_3d77.jpeg","s":"https://storage.googleapis.com/ltesoup/lte/9975_3d77.jpeg"},{"l":"https://storage.googleapis.com/ltesoup/lte/9636_abbd.jpeg","s":"https://storage.googleapis.com/ltesoup/lte/9636_abbd.jpeg"},{"l":"https://storage.googleapis.com/ltesoup/lte/2447_4e46.jpeg","s":"https://storage.googleapis.com/ltesoup/lte/2447_4e46.jpeg"},{"l":"https://storage.googleapis.com/ltesoup/lte/9039_9f0e.jpeg","s":"https://storage.googleapis.com/ltesoup/lte/9039_9f0e.jpeg"},{"l":"https://storage.googleapis.com/ltesoup/lte/9034_b0da.png","s":"https://storage.googleapis.com/ltesoup/lte/9034_b0da.png"},{"l":"https://storage.googleapis.com/ltesoup/lte/9014_6115.jpeg","s":"https://storage.googleapis.com/ltesoup/lte/9014_6115.jpeg"},{"l":"https://storage.googleapis.com/ltesoup/lte/9990_e058.jpeg","s":"https://storage.googleapis.com/ltesoup/lte/9990_e058.jpeg"}]