[{"l":"https://storage.googleapis.com/ltesoup/lte/1518_31c8.jpeg","s":"https://storage.googleapis.com/ltesoup/lte/1518_31c8.jpeg"},{"l":"https://storage.googleapis.com/ltesoup/lte/2112_a4f2.jpeg","s":"https://storage.googleapis.com/ltesoup/lte/2112_a4f2.jpeg"},{"l":"https://storage.googleapis.com/ltesoup/lte/9982_0aff.jpeg","s":"https://storage.googleapis.com/ltesoup/lte/9982_0aff.jpeg"},{"l":"https://storage.googleapis.com/ltesoup/lte/0437_5f60.png","s":"https://storage.googleapis.com/ltesoup/lte/0437_5f60.png"},{"l":"https://storage.googleapis.com/ltesoup/lte/0071_495c.png","s":"https://storage.googleapis.com/ltesoup/lte/0071_495c.png"},{"l":"https://storage.googleapis.com/ltesoup/lte/1471_a08c.jpeg","s":"https://storage.googleapis.com/ltesoup/lte/1471_a08c.jpeg"},{"l":"https://storage.googleapis.com/ltesoup/lte/1787_6f35.jpeg","s":"https://storage.googleapis.com/ltesoup/lte/1787_6f35.jpeg"},{"l":"https://storage.googleapis.com/ltesoup/lte/0734_8ae2.jpeg","s":"https://storage.googleapis.com/ltesoup/lte/0734_8ae2.jpeg"},{"l":"https://storage.googleapis.com/ltesoup/lte/7718_2384.jpeg","s":"https://storage.googleapis.com/ltesoup/lte/7718_2384.jpeg"},{"l":"https://storage.googleapis.com/ltesoup/lte/4260_5e17.png","s":"https://storage.googleapis.com/ltesoup/lte/4260_5e17.png"},{"l":"https://storage.googleapis.com/ltesoup/lte/2667_819a.png","s":"https://storage.googleapis.com/ltesoup/lte/2667_819a.png"},{"l":"https://storage.googleapis.com/ltesoup/lte/4046_ddc3.jpeg","s":"https://storage.googleapis.com/ltesoup/lte/4046_ddc3.jpeg"},{"l":"https://storage.googleapis.com/ltesoup/lte/4087_a5b7.jpeg","s":"https://storage.googleapis.com/ltesoup/lte/4087_a5b7.jpeg"},{"l":"https://storage.googleapis.com/ltesoup/lte/2793_e929.jpeg","s":"https://storage.googleapis.com/ltesoup/lte/2793_e929.jpeg"},{"l":"https://storage.googleapis.com/ltesoup/lte/2009_c6dd.png","s":"https://storage.googleapis.com/ltesoup/lte/2009_c6dd.png"},{"l":"https://storage.googleapis.com/ltesoup/lte/2481_719b.jpeg","s":"https://storage.googleapis.com/ltesoup/lte/2481_719b.jpeg"},{"l":"https://storage.googleapis.com/ltesoup/lte/2484_e572.jpeg","s":"https://storage.googleapis.com/ltesoup/lte/2484_e572.jpeg"},{"l":"https://storage.googleapis.com/ltesoup/lte/2564_2093.jpeg","s":"https://storage.googleapis.com/ltesoup/lte/2564_2093.jpeg"},{"l":"https://storage.googleapis.com/ltesoup/lte/7806_fc7c.jpeg","s":"https://storage.googleapis.com/ltesoup/lte/7806_fc7c.jpeg"},{"l":"https://storage.googleapis.com/ltesoup/lte/6483_b2d0.jpeg","s":"https://storage.googleapis.com/ltesoup/lte/6483_b2d0.jpeg"}]