[{"l":"https://storage.googleapis.com/ltesoup/lte/9165_4da8.png","s":"https://storage.googleapis.com/ltesoup/lte/9165_4da8.png"},{"l":"https://storage.googleapis.com/ltesoup/lte/2347_969a.jpeg","s":"https://storage.googleapis.com/ltesoup/lte/2347_969a.jpeg"},{"l":"https://storage.googleapis.com/ltesoup/lte/2354_55c3.jpeg","s":"https://storage.googleapis.com/ltesoup/lte/2354_55c3.jpeg"},{"l":"https://storage.googleapis.com/ltesoup/lte/1027_666a.jpeg","s":"https://storage.googleapis.com/ltesoup/lte/1027_666a.jpeg"},{"l":"https://storage.googleapis.com/ltesoup/lte/1224_228c.jpeg","s":"https://storage.googleapis.com/ltesoup/lte/1224_228c.jpeg"},{"l":"https://storage.googleapis.com/ltesoup/lte/1553_9965.gif","s":"https://storage.googleapis.com/ltesoup/lte/1553_9965.gif"},{"l":"https://storage.googleapis.com/ltesoup/lte/1559_9a3b.jpeg","s":"https://storage.googleapis.com/ltesoup/lte/1559_9a3b.jpeg"},{"l":"https://storage.googleapis.com/ltesoup/lte/1560_d5aa.png","s":"https://storage.googleapis.com/ltesoup/lte/1560_d5aa.png"},{"l":"https://storage.googleapis.com/ltesoup/lte/6091_069d.jpeg","s":"https://storage.googleapis.com/ltesoup/lte/6091_069d.jpeg"},{"l":"https://storage.googleapis.com/ltesoup/lte/7057_ca3c.jpeg","s":"https://storage.googleapis.com/ltesoup/lte/7057_ca3c.jpeg"},{"l":"https://storage.googleapis.com/ltesoup/lte/9286_3538.jpeg","s":"https://storage.googleapis.com/ltesoup/lte/9286_3538.jpeg"},{"l":"https://storage.googleapis.com/ltesoup/lte/3216_58ee.png","s":"https://storage.googleapis.com/ltesoup/lte/3216_58ee.png"},{"l":"https://storage.googleapis.com/ltesoup/lte/9276_c903.jpeg","s":"https://storage.googleapis.com/ltesoup/lte/9276_c903.jpeg"},{"l":"https://storage.googleapis.com/ltesoup/lte/9286_0b9d.jpeg","s":"https://storage.googleapis.com/ltesoup/lte/9286_0b9d.jpeg"},{"l":"https://storage.googleapis.com/ltesoup/lte/2465_a3c6.jpeg","s":"https://storage.googleapis.com/ltesoup/lte/2465_a3c6.jpeg"},{"l":"https://storage.googleapis.com/ltesoup/lte/9068_bebd.jpeg","s":"https://storage.googleapis.com/ltesoup/lte/9068_bebd.jpeg"},{"l":"https://storage.googleapis.com/ltesoup/lte/0308_7a2f.png","s":"https://storage.googleapis.com/ltesoup/lte/0308_7a2f.png"},{"l":"https://storage.googleapis.com/ltesoup/lte/1703_e086.jpeg","s":"https://storage.googleapis.com/ltesoup/lte/1703_e086.jpeg"},{"l":"https://storage.googleapis.com/ltesoup/lte/3043_eebd.gif","s":"https://storage.googleapis.com/ltesoup/lte/3043_eebd.gif"},{"l":"https://storage.googleapis.com/ltesoup/lte/3918_bdb8.jpeg","s":"https://storage.googleapis.com/ltesoup/lte/3918_bdb8.jpeg"}]