[{"l":"https://storage.googleapis.com/ltesoup/lte/7449_a93c.jpeg","s":"https://storage.googleapis.com/ltesoup/lte/7449_a93c.jpeg"},{"l":"https://storage.googleapis.com/ltesoup/lte/6286_a0dc.gif","s":"https://storage.googleapis.com/ltesoup/lte/6286_a0dc.gif"},{"l":"https://storage.googleapis.com/ltesoup/lte/1170_e6ae.png","s":"https://storage.googleapis.com/ltesoup/lte/1170_e6ae.png"},{"l":"https://storage.googleapis.com/ltesoup/lte/2234_af81.jpeg","s":"https://storage.googleapis.com/ltesoup/lte/2234_af81.jpeg"},{"l":"https://storage.googleapis.com/ltesoup/lte/3379_5326.png","s":"https://storage.googleapis.com/ltesoup/lte/3379_5326.png"},{"l":"https://storage.googleapis.com/ltesoup/lte/3768_c09e.gif","s":"https://storage.googleapis.com/ltesoup/lte/3768_c09e.gif"},{"l":"https://storage.googleapis.com/ltesoup/lte/6083_087d.jpeg","s":"https://storage.googleapis.com/ltesoup/lte/6083_087d.jpeg"},{"l":"https://storage.googleapis.com/ltesoup/lte/3855_9be7.gif","s":"https://storage.googleapis.com/ltesoup/lte/3855_9be7.gif"},{"l":"https://storage.googleapis.com/ltesoup/lte/2398_0acf.gif","s":"https://storage.googleapis.com/ltesoup/lte/2398_0acf.gif"},{"l":"https://storage.googleapis.com/ltesoup/lte/0231_8129.gif","s":"https://storage.googleapis.com/ltesoup/lte/0231_8129.gif"},{"l":"https://storage.googleapis.com/ltesoup/lte/8595_bf25.jpeg","s":"https://storage.googleapis.com/ltesoup/lte/8595_bf25.jpeg"},{"l":"https://storage.googleapis.com/ltesoup/lte/2988_97a7.gif","s":"https://storage.googleapis.com/ltesoup/lte/2988_97a7.gif"},{"l":"https://storage.googleapis.com/ltesoup/lte/8014_2806.jpeg","s":"https://storage.googleapis.com/ltesoup/lte/8014_2806.jpeg"},{"l":"https://storage.googleapis.com/ltesoup/lte/3996_45db.jpeg","s":"https://storage.googleapis.com/ltesoup/lte/3996_45db.jpeg"},{"l":"https://storage.googleapis.com/ltesoup/lte/1031_cfe3.jpeg","s":"https://storage.googleapis.com/ltesoup/lte/1031_cfe3.jpeg"},{"l":"https://storage.googleapis.com/ltesoup/lte/0911_33bb.gif","s":"https://storage.googleapis.com/ltesoup/lte/0911_33bb.gif"},{"l":"https://storage.googleapis.com/ltesoup/lte/9884_be5f.jpeg","s":"https://storage.googleapis.com/ltesoup/lte/9884_be5f.jpeg"},{"l":"https://storage.googleapis.com/ltesoup/lte/7808_e237.jpeg","s":"https://storage.googleapis.com/ltesoup/lte/7808_e237.jpeg"},{"l":"https://storage.googleapis.com/ltesoup/lte/3037_27c6.jpeg","s":"https://storage.googleapis.com/ltesoup/lte/3037_27c6.jpeg"},{"l":"https://storage.googleapis.com/ltesoup/lte/4173_9e9e.gif","s":"https://storage.googleapis.com/ltesoup/lte/4173_9e9e.gif"}]